{
  "palette": {
    "neutral": {
      "white": "#FFFFFF",
      "50": "#ECEDEE",
      "100": "#DADBDD",
      "200": "#D0D1D4",
      "300": "#A1A4AA",
      "400": "#737780",
      "500": "#444955",
      "600": "#333740",
      "700": "#22252B",
      "800": "#111215",
      "black": "#000000"
    },
    "purple": {
      "50": "#F2F1FE",
      "100": "#E5E3FE",
      "200": "#CAC7FD",
      "300": "#B2AEFC",
      "400": "#9A95FB",
      "500": "#7B72F9",
      "600": "#635CC7",
      "700": "#4A4695",
      "800": "#312E64",
      "900": "#191732"
    },
    "green": {
      "50": "#E6F6E5",
      "100": "#C3E9BF",
      "200": "#A1DC9A",
      "300": "#86D280",
      "400": "#6BC766",
      "500": "#0DA500",
      "600": "#109204",
      "700": "#0C6304",
      "800": "#084503",
      "900": "#074302"
    },
    "red": {
      "50": "#FFE5E5",
      "100": "#FFBFBF",
      "200": "#FF9A9A",
      "300": "#FF8080",
      "400": "#FF6666",
      "500": "#FF0000",
      "600": "#BF0000",
      "700": "#800000",
      "800": "#400000"
    },
    "blue": {
      "50": "#E5E6FF",
      "100": "#BFC2FF",
      "200": "#999DFF",
      "300": "#8085FF",
      "400": "#666DFF",
      "500": "#000AFF",
      "600": "#0008BF",
      "700": "#000580",
      "800": "#000340"
    },
    "orange": {
      "50": "#FFF0E5",
      "100": "#FFDABF",
      "200": "#FFC499",
      "300": "#FFB580",
      "400": "#FFA666",
      "500": "#FF6B00",
      "600": "#BF5000",
      "700": "#803600",
      "800": "#401B00"
    },
    "score": {
      "green": "#6cde20",
      "grass": "#c1e01e",
      "yellow": "#ebc718",
      "orange": "#ed6711",
      "red": "#f00f0f"
    }
  },
  "typography": {
    "fontFamily": "Roboto",
    "headings": {
      "h0": { "fontSize": "40px", "lineHeight": "40px", "fontWeight": 700 },
      "h1": { "fontSize": "28px", "lineHeight": "34px", "fontWeight": 700 },
      "h2": { "fontSize": "24px", "lineHeight": "32px", "fontWeight": 700 },
      "h3": { "fontSize": "20px", "lineHeight": "26px", "fontWeight": 700 },
      "h4": { "fontSize": "16px", "lineHeight": "24px", "fontWeight": 700 }
    },
    "body": {
      "lg": { "fontSize": "20px", "lineHeight": "24px", "fontWeight": 400 },
      "base": { "fontSize": "16px", "lineHeight": "22px", "fontWeight": 400 },
      "sm": { "fontSize": "14px", "lineHeight": "16px", "fontWeight": 400 },
      "xs": { "fontSize": "12px", "lineHeight": "14px", "fontWeight": 400 }
    },
    "weights": {
      "light": 300,
      "normal": 400,
      "medium": 500,
      "semibold": 600,
      "bold": 700
    }
  },
  "spacing": {
    "0": "0px",
    "25": "1px",
    "50": "2px",
    "100": "4px",
    "200": "8px",
    "300": "12px",
    "400": "16px",
    "500": "20px",
    "600": "24px",
    "700": "28px",
    "800": "32px",
    "900": "40px",
    "1000": "48px",
    "1200": "64px"
  },
  "borderRadius": {
    "0": "0px",
    "100": "4px",
    "200": "8px",
    "300": "12px",
    "400": "16px",
    "600": "24px",
    "700": "28px",
    "full": "9999px"
  },
  "borderWidth": {
    "0": "0px",
    "25": "1px",
    "50": "2px",
    "100": "4px"
  }
}
